{
  "unversionedId": "programming/JavaScript/Arrays&Strings/Array Methods",
  "id": "programming/JavaScript/Arrays&Strings/Array Methods",
  "title": "Array Methods",
  "description": "at()",
  "source": "@site/docs/programming/JavaScript/Arrays&Strings/Array Methods.md",
  "sourceDirName": "programming/JavaScript/Arrays&Strings",
  "slug": "/programming/JavaScript/Arrays&Strings/Array Methods",
  "permalink": "/docs/programming/JavaScript/Arrays&Strings/Array Methods",
  "draft": false,
  "tags": [],
  "version": "current",
  "sidebarPosition": 1,
  "frontMatter": {
    "sidebar_position": 1
  },
  "sidebar": "tutorialSidebar",
  "previous": {
    "title": "Arrays/Strings",
    "permalink": "/docs/category/arraysstrings"
  },
  "next": {
    "title": "Projects",
    "permalink": "/docs/programming/JavaScript/Projects"
  }
}